{
  "obsifetch:show-obsifetch": [
    {
      "modifiers": [
        "Alt",
        "Mod"
      ],
      "key": "\\"
    }
  ],
  "obsifetch:show": [
    {
      "modifiers": [
        "Alt",
        "Mod"
      ],
      "key": "\\"
    }
  ],
  "keyshots:toggle-snake-case": [
    {
      "modifiers": [
        "Alt",
        "Mod"
      ],
      "key": "-"
    }
  ],
  "change-case:snake": [
    {
      "modifiers": [
        "Alt",
        "Shift"
      ],
      "key": "-"
    }
  ],
  "change-case:capital": [
    {
      "modifiers": [
        "Alt",
        "Shift"
      ],
      "key": "="
    }
  ]
}